QingsongXuexiWeijifenYiyanGudengbao/README.md
QingsongXuexiWeijifenYiyanGudengbao/__init__.py
QingsongXuexiWeijifenYiyanGudengbao/__main__.py
QingsongXuexiWeijifenYiyanGudengbao/file.epub
QingsongXuexiWeijifenYiyanGudengbao/index.html
QingsongXuexiWeijifenYiyanGudengbao/css/__init__.py
QingsongXuexiWeijifenYiyanGudengbao/css/annotations.css
QingsongXuexiWeijifenYiyanGudengbao/css/main.css
QingsongXuexiWeijifenYiyanGudengbao/css/normalize.css
QingsongXuexiWeijifenYiyanGudengbao/css/popup.css
QingsongXuexiWeijifenYiyanGudengbao/font/__init__.py
QingsongXuexiWeijifenYiyanGudengbao/font/fontello.eot
QingsongXuexiWeijifenYiyanGudengbao/font/fontello.svg
QingsongXuexiWeijifenYiyanGudengbao/font/fontello.ttf
QingsongXuexiWeijifenYiyanGudengbao/font/fontello.woff
QingsongXuexiWeijifenYiyanGudengbao/img/__init__.py
QingsongXuexiWeijifenYiyanGudengbao/img/annotator-glyph-sprite.png
QingsongXuexiWeijifenYiyanGudengbao/img/annotator-icon-sprite.png
QingsongXuexiWeijifenYiyanGudengbao/img/apple-touch-icon.png
QingsongXuexiWeijifenYiyanGudengbao/img/cancelfullscreen.png
QingsongXuexiWeijifenYiyanGudengbao/img/close.png
QingsongXuexiWeijifenYiyanGudengbao/img/fullscreen.png
QingsongXuexiWeijifenYiyanGudengbao/img/loader.gif
QingsongXuexiWeijifenYiyanGudengbao/img/menu-icon.png
QingsongXuexiWeijifenYiyanGudengbao/img/save.png
QingsongXuexiWeijifenYiyanGudengbao/img/saved.png
QingsongXuexiWeijifenYiyanGudengbao/img/settings-s.png
QingsongXuexiWeijifenYiyanGudengbao/img/settings.png
QingsongXuexiWeijifenYiyanGudengbao/img/star.png
QingsongXuexiWeijifenYiyanGudengbao/js/__init__.py
QingsongXuexiWeijifenYiyanGudengbao/js/epub.js
QingsongXuexiWeijifenYiyanGudengbao/js/epub.min.js
QingsongXuexiWeijifenYiyanGudengbao/js/epub.min.map
QingsongXuexiWeijifenYiyanGudengbao/js/hooks.min.js
QingsongXuexiWeijifenYiyanGudengbao/js/hooks.min.map
QingsongXuexiWeijifenYiyanGudengbao/js/reader.js
QingsongXuexiWeijifenYiyanGudengbao/js/reader.js.map
QingsongXuexiWeijifenYiyanGudengbao/js/reader.min.js
qingsong_xuexi_weijifen_yiyan_gudengbao-2024.3.2.0.dist-info/METADATA
qingsong_xuexi_weijifen_yiyan_gudengbao-2024.3.2.0.dist-info/WHEEL
qingsong_xuexi_weijifen_yiyan_gudengbao-2024.3.2.0.dist-info/entry_points.txt
qingsong_xuexi_weijifen_yiyan_gudengbao-2024.3.2.0.dist-info/top_level.txt
qingsong_xuexi_weijifen_yiyan_gudengbao-2024.3.2.0.dist-info/RECORD
